{"version": "1", "message": "ERROR: Hidden Testcases server unreachable.", "problem_id": "ads2_m1_a1_1", "user_id": "jannuprathyusha", "score": {"sample": {"0": {"execution_time": 0.372234582901001, "passed": true}, "1": {"execution_time": 0.43933629989624023, "passed": true}, "2": {"execution_time": 0.26528143882751465, "passed": false}, "3": {"execution_time": 0.4698500633239746, "passed": true}, "4": {"execution_time": 0.23903346061706543, "passed": true}, "5": {"execution_time": 0.2296159267425537, "passed": true}, "6": {"execution_time": 0.20123624801635742, "passed": true}, "7": {"execution_time": 0.36275577545166016, "passed": true}}}, "check_style_score": "0/1"}